{"step_index":5690,"source":"MODEL","type":"CODE_ACTION","status":"DONE","created_at":"2026-05-22T21:35:10Z","content":"Created At: 2026-05-22T21:35:10Z\nCompleted At: 2026-05-22T21:35:44Z\nThe following changes were made by the replace_file_content tool to: C:\\Users\\paulo\\antigravity\\Colaborh---Conectando-Talentos\\src\\components\\CompanyDashboard.tsx. If relevant, proactively run terminal commands to execute this code for the USER. Don't ask for permission.\n[diff_block_start]\n@@ -4408,6 +4408,46 @@\n                 exit={{ opacity: 0, y: -20 }}\n                 className=\"space-y-6 text-left\"\n               >\n+                {/* Menu de Sub-abas */}\n+                <div className=\"flex border-b border-slate-100 bg-slate-50/50 p-1.5 rounded-2xl gap-2 overflow-x-auto scrollbar-none mb-6 shrink-0\">\n+                  <button\n+                    type=\"button\"\n+                    onClick={() => setResultsSubTab('relatorios')}\n+                    className={`px-6 py-3 rounded-xl text-[10px] font-black uppercase tracking-wider whitespace-nowrap transition-all flex-1 text-center cursor-pointer ${\n+                      resultsSubTab === 'relatorios'\n+                        ? 'bg-white text-slate-900 shadow-md border border-slate-100/50'\n+                        : 'text-slate-400 hover:text-slate-700'\n+                    }`}\n+                    style={resultsSubTab === 'relatorios' ? { borderLeft: '3px solid #533af6' } : {}}\n+                  >\n+                    Relatórios de Candidatos\n+                  </button>\n+                  <button\n+                    type=\"button\"\n+                    onClick={() => setResultsSubTab('guia')}\n+                    className={`px-6 py-3 rounded-xl text-[10px] font-black uppercase tracking-wider whitespace-nowrap transition-all flex-1 text-center cursor-pointer ${\n+                      resultsSubTab === 'guia'\n+                        ? 'bg-white text-slate-900 shadow-md border border-slate-100/50'\n+                        : 'text-slate-400 hover:text-slate-700'\n+                    }`}\n+                    style={resultsSubTab === 'guia' ? { borderLeft: '3px solid #533af6' } : {}}\n+   \n<truncated 30004 bytes>\n {/* Dropdown de Seleção de Vaga */}\n+                        <div className=\"max-w-md space-y-2\">\n+                          <label className=\"text-[10px] font-black text-slate-500 uppercase tracking-widest block\">Selecione a Vaga Associada</label>\n+                          <select\n+                            value={selectedJobForCustom}\n+                            onChange={(e) => handleJobChangeForCustomQuestions(e.target.value)}\n+                            className=\"w-full px-5 py-4 bg-slate-50 hover:bg-slate-100 border border-slate-200/60 focus:border-[#533af6]/30 focus:bg-white rounded-2xl text-xs font-extrabold text-slate-800 transition-all outline-none\"\n+                          >\n+                            <option value=\"\">-- Escolha uma vaga --</option>\n+                            {companyJobs.map(job => (\n+                              <option key={job.id} value={job.id}>\n+                                {job.title} ({job.modality || 'Presencial'})\n+                              </option>\n+                            ))}\n+                          </select>\n+                        </div>\n+\n+                        {selectedJobForCustom ? (\n+                          <div className=\"space-y-6 pt-4 border-t border-slate-100\">\n+                            <div className=\"flex flex-col sm:flex-row justify-between items-start sm:items-center gap-4\">\n+                              <h4 className=\"text-xs font-black text-slate-800 uppercase tracking-widest\">Estrutura das Perguntas ({customQuestions.length})</h4>\n+                              \n                               );\n                             })}\n                           </tbody>\n[diff_block_end]\n\nPlease note that the above snippet only shows the MODIFIED lines from the last change. It shows up to 3 lines of unchanged lines before and after the modified lines. The actual file contents may have many more lines not shown.\n\nWe did our best to apply changes despite some inaccuracies. Double check if the edit applied is what you intended."}