{"step_index":4322,"source":"MODEL","type":"CODE_ACTION","status":"DONE","created_at":"2026-05-22T12:18:18Z","content":"Created At: 2026-05-22T12:18:18Z\nCompleted At: 2026-05-22T12:18:18Z\nThe following changes were made by the replace_file_content tool to: C:\\Users\\paulo\\antigravity\\Colaborh---Conectando-Talentos\\src\\components\\CompanyDashboard.tsx. If relevant, proactively run terminal commands to execute this code for the USER. Don't ask for permission.\n[diff_block_start]\n@@ -2418,11 +2418,11 @@\n \n                       // DISC status parsing\n                       const phoneStr = fullApp.candidate_phone || '';\n-                      const parts = phoneStr.split('===DISC===');\n+                      const parsedData = parseCandidatePhoneData(phoneStr);\n                       let discStatus = 'NONE';\n                       let D = 0, I = 0, S = 0, C = 0;\n-                      if (parts.length > 1) {\n-                        const discVal = parts[1].trim();\n+                      if (parsedData.disc) {\n+                        const discVal = parsedData.disc;\n                         if (discVal === 'PENDING') {\n                           discStatus = 'PENDING';\n                         } else if (discVal.startsWith('COMPLETED===')) {\n@@ -2440,6 +2440,7 @@\n                         matchScore,\n                         normalizedStatus,\n                         discStatus,\n+                        notes: parsedData.notes,\n                         D, I, S, C\n                       };\n                     });\n[diff_block_end]\n\nPlease note that the above snippet only shows the MODIFIED lines from the last change. It shows up to 3 lines of unchanged lines before and after the modified lines. The actual file contents may have many more lines not shown."}